savesubmitexam/__init__.py
savesubmitexam/notebook_path.py
savesubmitexam/savesubmitexam.py
savesubmitexam_sebastian_stigler-0.3.0.dist-info/LICENSE.txt
savesubmitexam_sebastian_stigler-0.3.0.dist-info/METADATA
savesubmitexam_sebastian_stigler-0.3.0.dist-info/WHEEL
savesubmitexam_sebastian_stigler-0.3.0.dist-info/top_level.txt
savesubmitexam_sebastian_stigler-0.3.0.dist-info/RECORD
