Metadata-Version: 2.1
Name: savesubmitexam-sebastian-stigler
Version: 0.3.0
Summary: Widget generator for exam submission via ExamUploader in tljh
Home-page: https://in-stigler.htw-aalen.de/gitea/tools/savesubmitexam
Author: Sebastian Stigler
Author-email: sebastian.stigler@hs-aalen.de
License: MIT
Project-URL: Documentation, https://pyscaffold.org/
Platform: any
Classifier: Development Status :: 4 - Beta
Classifier: Programming Language :: Python
License-File: LICENSE.txt
Requires-Dist: importlib-metadata ; python_version < "3.8"
Provides-Extra: testing
Requires-Dist: setuptools ; extra == 'testing'
Requires-Dist: pytest ; extra == 'testing'
Requires-Dist: pytest-cov ; extra == 'testing'
